twtr/__init__.py
twtr/cli.py
twtr-0.1.4.dist-info/METADATA
twtr-0.1.4.dist-info/WHEEL
twtr-0.1.4.dist-info/entry_points.txt
twtr-0.1.4.dist-info/licenses/LICENSE
twtr-0.1.4.dist-info/RECORD
