Metadata-Version: 2.4
Name: twtr
Version: 0.1.4
Summary: Minimal CLI to tweet via Twitter API.
Project-URL: homepage, https://github.com/kiankyars/twtr
Author: Kian Kyars
License-File: LICENSE
Requires-Python: >=3.8
Requires-Dist: dotenv>=0.9.9
Requires-Dist: tweepy
